xkcdscrape/__init__.py
xkcdscrape/xkcd.py
xkcd_scrape-0.5.0.dist-info/METADATA
xkcd_scrape-0.5.0.dist-info/WHEEL
xkcd_scrape-0.5.0.dist-info/LICENSE
xkcd_scrape-0.5.0.dist-info/RECORD
