Metadata-Version: 2.1
Name: xkcd-scrape
Version: 0.5.0
Summary: Scrape the XKCD comic archive
Home-page: https://codeberg.org/calamity/xkcd-scrape
License: MIT
Author: calamity
Author-email: clmty@vk.com
Requires-Python: >=3.10,<4.0
Classifier: License :: OSI Approved :: MIT License
Classifier: Programming Language :: Python :: 3
Classifier: Programming Language :: Python :: 3.10
Classifier: Programming Language :: Python :: 3.11
Requires-Dist: beautifulsoup4 (>=4.11.1,<5.0.0)
Requires-Dist: lxml (>=4.9.2,<5.0.0)
Requires-Dist: requests (>=2.28.2,<3.0.0)
Project-URL: Repository, https://codeberg.org/calamity/xkcd-scrape
